pihace/__init__.py
pihace/__main__.py
pihace/healthcheck.py
pihace/loader.py
pihace/system_info.py
pihace/types.py
pihace/utils.py
pihace/plugins/__init__.py
pihace/plugins/elasticsearch.py
pihace/plugins/http.py
pihace/plugins/influxdb.py
pihace/plugins/mongodb.py
pihace/plugins/mysql.py
pihace/providers/__init__.py
pihace/providers/prometheus.py
pihace/providers/web.py
pihace/pusher/__init__.py
pihace/pusher/elasticsearch.py
pihace/pusher/messaging.py
pihace/storage/__init__.py
pihace/storage/mongodb.py
pihace-1.0.0.dist-info/METADATA
pihace-1.0.0.dist-info/WHEEL
pihace-1.0.0.dist-info/top_level.txt
pihace-1.0.0.dist-info/RECORD
