Metadata-Version: 2.4
Name: pihace
Version: 1.0.0
Summary: Python Integrated Health Check - A modular and extensible health check system for services and system resources.
Home-page: https://github.com/ahmadzeinalwafi/pihace
Author: Ahmad Zein Al Wafi
Author-email: ahmadzeinalwafi@outlook.com
License: Apache-2.0
Project-URL: Source, https://github.com/ahmadzeinalwafi/pihace
Project-URL: Tracker, https://github.com/ahmadzeinalwafi/pihace/issues
Keywords: healthcheck monitoring system microservice infrastructure
Classifier: Development Status :: 3 - Alpha
Classifier: Intended Audience :: Developers
Classifier: Topic :: Software Development :: Libraries :: Python Modules
Classifier: Programming Language :: Python :: 3.10
Classifier: Programming Language :: Python :: 3.11
Classifier: Operating System :: OS Independent
Requires-Python: >=3.10
Requires-Dist: psutil>=5.9.0
Requires-Dist: pymongo>=4.3.0
Requires-Dist: mysql-connector-python>=8.0.30
Requires-Dist: influxdb-client>=1.36.0
Requires-Dist: requests>=2.32.3
Requires-Dist: elasticsearch==8.11.1
Requires-Dist: prometheus_client==0.21.1
Requires-Dist: pika==1.3.2
Requires-Dist: pyyaml>=6.0
Requires-Dist: fastapi>=0.115.0
Provides-Extra: dev
Requires-Dist: pytest; extra == "dev"
Requires-Dist: flake8; extra == "dev"
Dynamic: author
Dynamic: author-email
Dynamic: classifier
Dynamic: description
Dynamic: description-content-type
Dynamic: home-page
Dynamic: keywords
Dynamic: license
Dynamic: project-url
Dynamic: provides-extra
Dynamic: requires-dist
Dynamic: requires-python
Dynamic: summary
